README.md
setup.py
src/cazart/__init__.py
src/cazart/cazart.py
src/cazart/version.py
src/cazart.egg-info/PKG-INFO
src/cazart.egg-info/SOURCES.txt
src/cazart.egg-info/dependency_links.txt
src/cazart.egg-info/requires.txt
src/cazart.egg-info/top_level.txt
test/test_cazart.py