Metadata-Version: 2.1
Name: cazart
Version: 0.0.5
Summary: Flask + Schema = Cazart!
Home-page: https://github.com/woodruffw/cazart
Author: William Woodruff
Author-email: william@yossarian.net
License: MIT with restrictions
Platform: any
Requires-Python: >=3.6
Provides-Extra: dev
